[
	{
		"classifier_acc_dict": {
			"main": 0.0,
			"pp_emb_norm": 0.0,
			"main_xent": 0.0,
			"emb_norm": 14.206209182739258,
			"reg_loss": 0.20934779942035675,
			"reg_acc": 0.718856930732727,
			"rr_loss": 0.19195914268493652,
			"reg_loss_valid": 0.10216806828975677,
			"reg_acc_valid": 0.8716357350349426,
			"rr_loss_valid": 0.18886716663837433,
			"reg_loss_all": 0.0,
			"reg_acc_all": 0.0,
			"rr_loss_all": 0.0,
			"reg_loss_all_valid": 0.0,
			"reg_acc_all_valid": 0.0,
			"rr_loss_all_valid": 0.0,
			"tmle_loss": 0.4017535150051117,
			"l2_loss": 0.0,
			"te_train": 0.0018851484637707472,
			"te_corr_train": -0.003845554543659091,
			"te_dr_train": -0.005540147889405489,
			"te_valid": 0.05365902930498123,
			"te_corr_valid": 0.030821088701486588,
			"te_dr_valid": 0.06708072125911713,
			"alpha:t00-tcf0": 0.0,
			"alpha:t00-tcf1": 0.0,
			"alpha:t01-tcf0": 0.0,
			"alpha:t01-tcf1": 0.0,
			"topic0": 0.0,
			"topic0_flip_main": 0.0,
			"topic0_smin_main": 0.0,
			"main_smin_topic0": 0.0,
			"topic0_flip_main_pdelta": 0.0,
			"topic0_flip_main_logpdelta": 0.0,
			"topic0_flip_emb_diff": 0.0,
			"topic0_flip_main_pdelta_m1t1": 0.0,
			"topic0_flip_main_pdelta_m0t1": 0.0,
			"topic0_flip_main_pdelta_m0t0": 0.0,
			"topic0_flip_main_pdelta_m1t0": 0.0,
			"topic0_flip_main_pdelta_smin": 0.0,
			"topic0_flip_main_pdelta_smaj": 0.0,
			"topic0_flip_main_pdelta_all": 0.0,
			"topic0_pos_con_loss": 0.0,
			"topic0_neg_con_loss": 0.0,
			"topic0_last_emb_norm": 0.0,
			"topic0_te_loss": 0.0
		},
		"label_corr_dict": null
	},
	{
		"classifier_acc_dict": {
			"main": 0.0,
			"pp_emb_norm": 0.0,
			"main_xent": 0.0,
			"emb_norm": 14.574126243591309,
			"reg_loss": 0.0719979777932167,
			"reg_acc": 0.9108565449714661,
			"rr_loss": 0.17371733486652374,
			"reg_loss_valid": 0.09873270988464355,
			"reg_acc_valid": 0.8881989121437073,
			"rr_loss_valid": 0.1696700155735016,
			"reg_loss_all": 0.0,
			"reg_acc_all": 0.0,
			"rr_loss_all": 0.0,
			"reg_loss_all_valid": 0.0,
			"reg_acc_all_valid": 0.0,
			"rr_loss_all_valid": 0.0,
			"tmle_loss": 0.2157352715730667,
			"l2_loss": 0.0,
			"te_train": 0.047283515334129333,
			"te_corr_train": 0.0327516533434391,
			"te_dr_train": 0.04620013386011124,
			"te_valid": 0.06041228771209717,
			"te_corr_valid": 0.03710512816905975,
			"te_dr_valid": 0.05539138615131378,
			"alpha:t00-tcf0": 0.0,
			"alpha:t00-tcf1": 0.0,
			"alpha:t01-tcf0": 0.0,
			"alpha:t01-tcf1": 0.0,
			"topic0": 0.0,
			"topic0_flip_main": 0.0,
			"topic0_smin_main": 0.0,
			"main_smin_topic0": 0.0,
			"topic0_flip_main_pdelta": 0.0,
			"topic0_flip_main_logpdelta": 0.0,
			"topic0_flip_emb_diff": 0.0,
			"topic0_flip_main_pdelta_m1t1": 0.0,
			"topic0_flip_main_pdelta_m0t1": 0.0,
			"topic0_flip_main_pdelta_m0t0": 0.0,
			"topic0_flip_main_pdelta_m1t0": 0.0,
			"topic0_flip_main_pdelta_smin": 0.0,
			"topic0_flip_main_pdelta_smaj": 0.0,
			"topic0_flip_main_pdelta_all": 0.0,
			"topic0_pos_con_loss": 0.0,
			"topic0_neg_con_loss": 0.0,
			"topic0_last_emb_norm": 0.0,
			"topic0_te_loss": 0.0
		},
		"label_corr_dict": null
	},
	{
		"classifier_acc_dict": {
			"main": 0.0,
			"pp_emb_norm": 0.0,
			"main_xent": 0.0,
			"emb_norm": 14.904071807861328,
			"reg_loss": 0.030637407675385475,
			"reg_acc": 0.9737141132354736,
			"rr_loss": 0.14645986258983612,
			"reg_loss_valid": 0.1069788709282875,
			"reg_acc_valid": 0.8881988525390625,
			"rr_loss_valid": 0.10102251172065735,
			"reg_loss_all": 0.0,
			"reg_acc_all": 0.0,
			"rr_loss_all": 0.0,
			"reg_loss_all_valid": 0.0,
			"reg_acc_all_valid": 0.0,
			"rr_loss_all_valid": 0.0,
			"tmle_loss": 0.15337474644184113,
			"l2_loss": 0.0,
			"te_train": 0.03874007612466812,
			"te_corr_train": 0.02946946956217289,
			"te_dr_train": 0.039275914430618286,
			"te_valid": 0.05429110676050186,
			"te_corr_valid": 0.046454884111881256,
			"te_dr_valid": 0.06419950723648071,
			"alpha:t00-tcf0": 0.0,
			"alpha:t00-tcf1": 0.0,
			"alpha:t01-tcf0": 0.0,
			"alpha:t01-tcf1": 0.0,
			"topic0": 0.0,
			"topic0_flip_main": 0.0,
			"topic0_smin_main": 0.0,
			"main_smin_topic0": 0.0,
			"topic0_flip_main_pdelta": 0.0,
			"topic0_flip_main_logpdelta": 0.0,
			"topic0_flip_emb_diff": 0.0,
			"topic0_flip_main_pdelta_m1t1": 0.0,
			"topic0_flip_main_pdelta_m0t1": 0.0,
			"topic0_flip_main_pdelta_m0t0": 0.0,
			"topic0_flip_main_pdelta_m1t0": 0.0,
			"topic0_flip_main_pdelta_smin": 0.0,
			"topic0_flip_main_pdelta_smaj": 0.0,
			"topic0_flip_main_pdelta_all": 0.0,
			"topic0_pos_con_loss": 0.0,
			"topic0_neg_con_loss": 0.0,
			"topic0_last_emb_norm": 0.0,
			"topic0_te_loss": 0.0
		},
		"label_corr_dict": null
	},
	{
		"classifier_acc_dict": {
			"main": 0.0,
			"pp_emb_norm": 0.0,
			"main_xent": 0.0,
			"emb_norm": 15.265830993652344,
			"reg_loss": 0.021450873464345932,
			"reg_acc": 0.9845712780952454,
			"rr_loss": 0.11842180043458939,
			"reg_loss_valid": 0.11837054044008255,
			"reg_acc_valid": 0.8488613963127136,
			"rr_loss_valid": 0.16081148386001587,
			"reg_loss_all": 0.0,
			"reg_acc_all": 0.0,
			"rr_loss_all": 0.0,
			"reg_loss_all_valid": 0.0,
			"reg_acc_all_valid": 0.0,
			"rr_loss_all_valid": 0.0,
			"tmle_loss": 0.12091241776943207,
			"l2_loss": 0.0,
			"te_train": 0.04669247195124626,
			"te_corr_train": 0.042372144758701324,
			"te_dr_train": 0.048002470284700394,
			"te_valid": 0.07863695174455643,
			"te_corr_valid": 0.048274241387844086,
			"te_dr_valid": 0.0812092274427414,
			"alpha:t00-tcf0": 0.0,
			"alpha:t00-tcf1": 0.0,
			"alpha:t01-tcf0": 0.0,
			"alpha:t01-tcf1": 0.0,
			"topic0": 0.0,
			"topic0_flip_main": 0.0,
			"topic0_smin_main": 0.0,
			"main_smin_topic0": 0.0,
			"topic0_flip_main_pdelta": 0.0,
			"topic0_flip_main_logpdelta": 0.0,
			"topic0_flip_emb_diff": 0.0,
			"topic0_flip_main_pdelta_m1t1": 0.0,
			"topic0_flip_main_pdelta_m0t1": 0.0,
			"topic0_flip_main_pdelta_m0t0": 0.0,
			"topic0_flip_main_pdelta_m1t0": 0.0,
			"topic0_flip_main_pdelta_smin": 0.0,
			"topic0_flip_main_pdelta_smaj": 0.0,
			"topic0_flip_main_pdelta_all": 0.0,
			"topic0_pos_con_loss": 0.0,
			"topic0_neg_con_loss": 0.0,
			"topic0_last_emb_norm": 0.0,
			"topic0_te_loss": 0.0
		},
		"label_corr_dict": null
	},
	{
		"classifier_acc_dict": {
			"main": 0.0,
			"pp_emb_norm": 0.0,
			"main_xent": 0.0,
			"emb_norm": 14.928647994995117,
			"reg_loss": 0.013446114026010036,
			"reg_acc": 0.9879999160766602,
			"rr_loss": 0.1622261106967926,
			"reg_loss_valid": 0.1276293247938156,
			"reg_acc_valid": 0.8488615155220032,
			"rr_loss_valid": 0.1905294805765152,
			"reg_loss_all": 0.0,
			"reg_acc_all": 0.0,
			"rr_loss_all": 0.0,
			"reg_loss_all_valid": 0.0,
			"reg_acc_all_valid": 0.0,
			"rr_loss_all_valid": 0.0,
			"tmle_loss": 0.14646723866462708,
			"l2_loss": 0.0,
			"te_train": 0.0459883026778698,
			"te_corr_train": 0.034001801162958145,
			"te_dr_train": 0.045420531183481216,
			"te_valid": 0.036805517971515656,
			"te_corr_valid": 0.021849870681762695,
			"te_dr_valid": 0.09641767293214798,
			"alpha:t00-tcf0": 0.0,
			"alpha:t00-tcf1": 0.0,
			"alpha:t01-tcf0": 0.0,
			"alpha:t01-tcf1": 0.0,
			"topic0": 0.0,
			"topic0_flip_main": 0.0,
			"topic0_smin_main": 0.0,
			"main_smin_topic0": 0.0,
			"topic0_flip_main_pdelta": 0.0,
			"topic0_flip_main_logpdelta": 0.0,
			"topic0_flip_emb_diff": 0.0,
			"topic0_flip_main_pdelta_m1t1": 0.0,
			"topic0_flip_main_pdelta_m0t1": 0.0,
			"topic0_flip_main_pdelta_m0t0": 0.0,
			"topic0_flip_main_pdelta_m1t0": 0.0,
			"topic0_flip_main_pdelta_smin": 0.0,
			"topic0_flip_main_pdelta_smaj": 0.0,
			"topic0_flip_main_pdelta_all": 0.0,
			"topic0_pos_con_loss": 0.0,
			"topic0_neg_con_loss": 0.0,
			"topic0_last_emb_norm": 0.0,
			"topic0_te_loss": 0.0
		},
		"label_corr_dict": null
	},
	{
		"classifier_acc_dict": {
			"main": 0.0,
			"pp_emb_norm": 0.0,
			"main_xent": 0.0,
			"emb_norm": 15.13720703125,
			"reg_loss": 0.005511377938091755,
			"reg_acc": 0.9959999322891235,
			"rr_loss": 0.18520395457744598,
			"reg_loss_valid": 0.113226979970932,
			"reg_acc_valid": 0.8716357350349426,
			"rr_loss_valid": 0.2142617553472519,
			"reg_loss_all": 0.0,
			"reg_acc_all": 0.0,
			"rr_loss_all": 0.0,
			"reg_loss_all_valid": 0.0,
			"reg_acc_all_valid": 0.0,
			"rr_loss_all_valid": 0.0,
			"tmle_loss": 0.15897248685359955,
			"l2_loss": 0.0,
			"te_train": 0.04085004702210426,
			"te_corr_train": 0.025258686393499374,
			"te_dr_train": 0.040543653070926666,
			"te_valid": 0.054668743163347244,
			"te_corr_valid": 0.02798314020037651,
			"te_dr_valid": 0.09120705723762512,
			"alpha:t00-tcf0": 0.0,
			"alpha:t00-tcf1": 0.0,
			"alpha:t01-tcf0": 0.0,
			"alpha:t01-tcf1": 0.0,
			"topic0": 0.0,
			"topic0_flip_main": 0.0,
			"topic0_smin_main": 0.0,
			"main_smin_topic0": 0.0,
			"topic0_flip_main_pdelta": 0.0,
			"topic0_flip_main_logpdelta": 0.0,
			"topic0_flip_emb_diff": 0.0,
			"topic0_flip_main_pdelta_m1t1": 0.0,
			"topic0_flip_main_pdelta_m0t1": 0.0,
			"topic0_flip_main_pdelta_m0t0": 0.0,
			"topic0_flip_main_pdelta_m1t0": 0.0,
			"topic0_flip_main_pdelta_smin": 0.0,
			"topic0_flip_main_pdelta_smaj": 0.0,
			"topic0_flip_main_pdelta_all": 0.0,
			"topic0_pos_con_loss": 0.0,
			"topic0_neg_con_loss": 0.0,
			"topic0_last_emb_norm": 0.0,
			"topic0_te_loss": 0.0
		},
		"label_corr_dict": null
	},
	{
		"classifier_acc_dict": {
			"main": 0.0,
			"pp_emb_norm": 0.0,
			"main_xent": 0.0,
			"emb_norm": 15.199689865112305,
			"reg_loss": 0.0029473835602402687,
			"reg_acc": 0.9988571405410767,
			"rr_loss": 0.19955120980739594,
			"reg_loss_valid": 0.10849662125110626,
			"reg_acc_valid": 0.877846896648407,
			"rr_loss_valid": 0.22290237247943878,
			"reg_loss_all": 0.0,
			"reg_acc_all": 0.0,
			"rr_loss_all": 0.0,
			"reg_loss_all_valid": 0.0,
			"reg_acc_all_valid": 0.0,
			"rr_loss_all_valid": 0.0,
			"tmle_loss": 0.16615864634513855,
			"l2_loss": 0.0,
			"te_train": 0.040379516780376434,
			"te_corr_train": 0.022499777376651764,
			"te_dr_train": 0.04060070961713791,
			"te_valid": 0.058148376643657684,
			"te_corr_valid": 0.027706777676939964,
			"te_dr_valid": 0.07908418029546738,
			"alpha:t00-tcf0": 0.0,
			"alpha:t00-tcf1": 0.0,
			"alpha:t01-tcf0": 0.0,
			"alpha:t01-tcf1": 0.0,
			"topic0": 0.0,
			"topic0_flip_main": 0.0,
			"topic0_smin_main": 0.0,
			"main_smin_topic0": 0.0,
			"topic0_flip_main_pdelta": 0.0,
			"topic0_flip_main_logpdelta": 0.0,
			"topic0_flip_emb_diff": 0.0,
			"topic0_flip_main_pdelta_m1t1": 0.0,
			"topic0_flip_main_pdelta_m0t1": 0.0,
			"topic0_flip_main_pdelta_m0t0": 0.0,
			"topic0_flip_main_pdelta_m1t0": 0.0,
			"topic0_flip_main_pdelta_smin": 0.0,
			"topic0_flip_main_pdelta_smaj": 0.0,
			"topic0_flip_main_pdelta_all": 0.0,
			"topic0_pos_con_loss": 0.0,
			"topic0_neg_con_loss": 0.0,
			"topic0_last_emb_norm": 0.0,
			"topic0_te_loss": 0.0
		},
		"label_corr_dict": null
	},
	{
		"classifier_acc_dict": {
			"main": 0.0,
			"pp_emb_norm": 0.0,
			"main_xent": 0.0,
			"emb_norm": 15.192538261413574,
			"reg_loss": 0.001454695244319737,
			"reg_acc": 0.9994285702705383,
			"rr_loss": 0.20640186965465546,
			"reg_loss_valid": 0.1112009808421135,
			"reg_acc_valid": 0.8716357350349426,
			"rr_loss_valid": 0.22489334642887115,
			"reg_loss_all": 0.0,
			"reg_acc_all": 0.0,
			"rr_loss_all": 0.0,
			"reg_loss_all_valid": 0.0,
			"reg_acc_all_valid": 0.0,
			"rr_loss_all_valid": 0.0,
			"tmle_loss": 0.17087723314762115,
			"l2_loss": 0.0,
			"te_train": 0.038713376969099045,
			"te_corr_train": 0.020399579778313637,
			"te_dr_train": 0.038804300129413605,
			"te_valid": 0.06026453152298927,
			"te_corr_valid": 0.027573106810450554,
			"te_dr_valid": 0.07144108414649963,
			"alpha:t00-tcf0": 0.0,
			"alpha:t00-tcf1": 0.0,
			"alpha:t01-tcf0": 0.0,
			"alpha:t01-tcf1": 0.0,
			"topic0": 0.0,
			"topic0_flip_main": 0.0,
			"topic0_smin_main": 0.0,
			"main_smin_topic0": 0.0,
			"topic0_flip_main_pdelta": 0.0,
			"topic0_flip_main_logpdelta": 0.0,
			"topic0_flip_emb_diff": 0.0,
			"topic0_flip_main_pdelta_m1t1": 0.0,
			"topic0_flip_main_pdelta_m0t1": 0.0,
			"topic0_flip_main_pdelta_m0t0": 0.0,
			"topic0_flip_main_pdelta_m1t0": 0.0,
			"topic0_flip_main_pdelta_smin": 0.0,
			"topic0_flip_main_pdelta_smaj": 0.0,
			"topic0_flip_main_pdelta_all": 0.0,
			"topic0_pos_con_loss": 0.0,
			"topic0_neg_con_loss": 0.0,
			"topic0_last_emb_norm": 0.0,
			"topic0_te_loss": 0.0
		},
		"label_corr_dict": null
	},
	{
		"classifier_acc_dict": {
			"main": 0.0,
			"pp_emb_norm": 0.0,
			"main_xent": 0.0,
			"emb_norm": 15.176267623901367,
			"reg_loss": 0.0011410537408664823,
			"reg_acc": 0.9988571405410767,
			"rr_loss": 0.20598314702510834,
			"reg_loss_valid": 0.1108478456735611,
			"reg_acc_valid": 0.8716357350349426,
			"rr_loss_valid": 0.22400042414665222,
			"reg_loss_all": 0.0,
			"reg_acc_all": 0.0,
			"rr_loss_all": 0.0,
			"reg_loss_all_valid": 0.0,
			"reg_acc_all_valid": 0.0,
			"rr_loss_all_valid": 0.0,
			"tmle_loss": 0.17114286124706268,
			"l2_loss": 0.0,
			"te_train": 0.03722374513745308,
			"te_corr_train": 0.019400473684072495,
			"te_dr_train": 0.037352826446294785,
			"te_valid": 0.060548387467861176,
			"te_corr_valid": 0.028135621920228004,
			"te_dr_valid": 0.06897442787885666,
			"alpha:t00-tcf0": 0.0,
			"alpha:t00-tcf1": 0.0,
			"alpha:t01-tcf0": 0.0,
			"alpha:t01-tcf1": 0.0,
			"topic0": 0.0,
			"topic0_flip_main": 0.0,
			"topic0_smin_main": 0.0,
			"main_smin_topic0": 0.0,
			"topic0_flip_main_pdelta": 0.0,
			"topic0_flip_main_logpdelta": 0.0,
			"topic0_flip_emb_diff": 0.0,
			"topic0_flip_main_pdelta_m1t1": 0.0,
			"topic0_flip_main_pdelta_m0t1": 0.0,
			"topic0_flip_main_pdelta_m0t0": 0.0,
			"topic0_flip_main_pdelta_m1t0": 0.0,
			"topic0_flip_main_pdelta_smin": 0.0,
			"topic0_flip_main_pdelta_smaj": 0.0,
			"topic0_flip_main_pdelta_all": 0.0,
			"topic0_pos_con_loss": 0.0,
			"topic0_neg_con_loss": 0.0,
			"topic0_last_emb_norm": 0.0,
			"topic0_te_loss": 0.0
		},
		"label_corr_dict": null
	},
	{
		"classifier_acc_dict": {
			"main": 0.0,
			"pp_emb_norm": 0.0,
			"main_xent": 0.0,
			"emb_norm": 15.18040943145752,
			"reg_loss": 0.0010408535599708557,
			"reg_acc": 0.9988571405410767,
			"rr_loss": 0.20871856808662415,
			"reg_loss_valid": 0.11072705686092377,
			"reg_acc_valid": 0.8716357350349426,
			"rr_loss_valid": 0.22448600828647614,
			"reg_loss_all": 0.0,
			"reg_acc_all": 0.0,
			"rr_loss_all": 0.0,
			"reg_loss_all_valid": 0.0,
			"reg_acc_all_valid": 0.0,
			"rr_loss_all_valid": 0.0,
			"tmle_loss": 0.1722954511642456,
			"l2_loss": 0.0,
			"te_train": 0.03811047971248627,
			"te_corr_train": 0.019477874040603638,
			"te_dr_train": 0.03817201033234596,
			"te_valid": 0.06042437627911568,
			"te_corr_valid": 0.02815616875886917,
			"te_dr_valid": 0.0668497234582901,
			"alpha:t00-tcf0": 0.0,
			"alpha:t00-tcf1": 0.0,
			"alpha:t01-tcf0": 0.0,
			"alpha:t01-tcf1": 0.0,
			"topic0": 0.0,
			"topic0_flip_main": 0.0,
			"topic0_smin_main": 0.0,
			"main_smin_topic0": 0.0,
			"topic0_flip_main_pdelta": 0.0,
			"topic0_flip_main_logpdelta": 0.0,
			"topic0_flip_emb_diff": 0.0,
			"topic0_flip_main_pdelta_m1t1": 0.0,
			"topic0_flip_main_pdelta_m0t1": 0.0,
			"topic0_flip_main_pdelta_m0t0": 0.0,
			"topic0_flip_main_pdelta_m1t0": 0.0,
			"topic0_flip_main_pdelta_smin": 0.0,
			"topic0_flip_main_pdelta_smaj": 0.0,
			"topic0_flip_main_pdelta_all": 0.0,
			"topic0_pos_con_loss": 0.0,
			"topic0_neg_con_loss": 0.0,
			"topic0_last_emb_norm": 0.0,
			"topic0_te_loss": 0.0
		},
		"label_corr_dict": null
	},
	{
		"classifier_acc_dict": {
			"main": 0.0,
			"pp_emb_norm": 0.0,
			"main_xent": 0.0,
			"emb_norm": 15.166535377502441,
			"reg_loss": 0.0010163098340854049,
			"reg_acc": 0.9988571405410767,
			"rr_loss": 0.21035529673099518,
			"reg_loss_valid": 0.11156477779150009,
			"reg_acc_valid": 0.8695653080940247,
			"rr_loss_valid": 0.2252676784992218,
			"reg_loss_all": 0.0,
			"reg_acc_all": 0.0,
			"rr_loss_all": 0.0,
			"reg_loss_all_valid": 0.0,
			"reg_acc_all_valid": 0.0,
			"rr_loss_all_valid": 0.0,
			"tmle_loss": 0.17320898175239563,
			"l2_loss": 0.0,
			"te_train": 0.038806378841400146,
			"te_corr_train": 0.019858557730913162,
			"te_dr_train": 0.03886650130152702,
			"te_valid": 0.060788437724113464,
			"te_corr_valid": 0.02792585827410221,
			"te_dr_valid": 0.06578104943037033,
			"alpha:t00-tcf0": 0.0,
			"alpha:t00-tcf1": 0.0,
			"alpha:t01-tcf0": 0.0,
			"alpha:t01-tcf1": 0.0,
			"topic0": 0.0,
			"topic0_flip_main": 0.0,
			"topic0_smin_main": 0.0,
			"main_smin_topic0": 0.0,
			"topic0_flip_main_pdelta": 0.0,
			"topic0_flip_main_logpdelta": 0.0,
			"topic0_flip_emb_diff": 0.0,
			"topic0_flip_main_pdelta_m1t1": 0.0,
			"topic0_flip_main_pdelta_m0t1": 0.0,
			"topic0_flip_main_pdelta_m0t0": 0.0,
			"topic0_flip_main_pdelta_m1t0": 0.0,
			"topic0_flip_main_pdelta_smin": 0.0,
			"topic0_flip_main_pdelta_smaj": 0.0,
			"topic0_flip_main_pdelta_all": 0.0,
			"topic0_pos_con_loss": 0.0,
			"topic0_neg_con_loss": 0.0,
			"topic0_last_emb_norm": 0.0,
			"topic0_te_loss": 0.0
		},
		"label_corr_dict": null
	},
	{
		"classifier_acc_dict": {
			"main": 0.0,
			"pp_emb_norm": 0.0,
			"main_xent": 0.0,
			"emb_norm": 15.156026840209961,
			"reg_loss": 0.0010426061926409602,
			"reg_acc": 0.9988571405410767,
			"rr_loss": 0.21172770857810974,
			"reg_loss_valid": 0.11265435814857483,
			"reg_acc_valid": 0.8674949407577515,
			"rr_loss_valid": 0.22646984457969666,
			"reg_loss_all": 0.0,
			"reg_acc_all": 0.0,
			"rr_loss_all": 0.0,
			"reg_loss_all_valid": 0.0,
			"reg_acc_all_valid": 0.0,
			"rr_loss_all_valid": 0.0,
			"tmle_loss": 0.17358431220054626,
			"l2_loss": 0.0,
			"te_train": 0.03911735862493515,
			"te_corr_train": 0.019754158332943916,
			"te_dr_train": 0.03918123245239258,
			"te_valid": 0.0616975799202919,
			"te_corr_valid": 0.027821488678455353,
			"te_dr_valid": 0.06421038508415222,
			"alpha:t00-tcf0": 0.0,
			"alpha:t00-tcf1": 0.0,
			"alpha:t01-tcf0": 0.0,
			"alpha:t01-tcf1": 0.0,
			"topic0": 0.0,
			"topic0_flip_main": 0.0,
			"topic0_smin_main": 0.0,
			"main_smin_topic0": 0.0,
			"topic0_flip_main_pdelta": 0.0,
			"topic0_flip_main_logpdelta": 0.0,
			"topic0_flip_emb_diff": 0.0,
			"topic0_flip_main_pdelta_m1t1": 0.0,
			"topic0_flip_main_pdelta_m0t1": 0.0,
			"topic0_flip_main_pdelta_m0t0": 0.0,
			"topic0_flip_main_pdelta_m1t0": 0.0,
			"topic0_flip_main_pdelta_smin": 0.0,
			"topic0_flip_main_pdelta_smaj": 0.0,
			"topic0_flip_main_pdelta_all": 0.0,
			"topic0_pos_con_loss": 0.0,
			"topic0_neg_con_loss": 0.0,
			"topic0_last_emb_norm": 0.0,
			"topic0_te_loss": 0.0
		},
		"label_corr_dict": null
	},
	{
		"classifier_acc_dict": {
			"main": 0.0,
			"pp_emb_norm": 0.0,
			"main_xent": 0.0,
			"emb_norm": 15.147923469543457,
			"reg_loss": 0.0011388609418645501,
			"reg_acc": 0.9988571405410767,
			"rr_loss": 0.20851808786392212,
			"reg_loss_valid": 0.11192546039819717,
			"reg_acc_valid": 0.8674949407577515,
			"rr_loss_valid": 0.22749905288219452,
			"reg_loss_all": 0.0,
			"reg_acc_all": 0.0,
			"rr_loss_all": 0.0,
			"reg_loss_all_valid": 0.0,
			"reg_acc_all_valid": 0.0,
			"rr_loss_all_valid": 0.0,
			"tmle_loss": 0.1725141853094101,
			"l2_loss": 0.0,
			"te_train": 0.03739441931247711,
			"te_corr_train": 0.019077392295002937,
			"te_dr_train": 0.03749430552124977,
			"te_valid": 0.06201549246907234,
			"te_corr_valid": 0.02807879075407982,
			"te_dr_valid": 0.0634225532412529,
			"alpha:t00-tcf0": 0.0,
			"alpha:t00-tcf1": 0.0,
			"alpha:t01-tcf0": 0.0,
			"alpha:t01-tcf1": 0.0,
			"topic0": 0.0,
			"topic0_flip_main": 0.0,
			"topic0_smin_main": 0.0,
			"main_smin_topic0": 0.0,
			"topic0_flip_main_pdelta": 0.0,
			"topic0_flip_main_logpdelta": 0.0,
			"topic0_flip_emb_diff": 0.0,
			"topic0_flip_main_pdelta_m1t1": 0.0,
			"topic0_flip_main_pdelta_m0t1": 0.0,
			"topic0_flip_main_pdelta_m0t0": 0.0,
			"topic0_flip_main_pdelta_m1t0": 0.0,
			"topic0_flip_main_pdelta_smin": 0.0,
			"topic0_flip_main_pdelta_smaj": 0.0,
			"topic0_flip_main_pdelta_all": 0.0,
			"topic0_pos_con_loss": 0.0,
			"topic0_neg_con_loss": 0.0,
			"topic0_last_emb_norm": 0.0,
			"topic0_te_loss": 0.0
		},
		"label_corr_dict": null
	},
	{
		"classifier_acc_dict": {
			"main": 0.0,
			"pp_emb_norm": 0.0,
			"main_xent": 0.0,
			"emb_norm": 15.163260459899902,
			"reg_loss": 0.0011356056202203035,
			"reg_acc": 0.9988571405410767,
			"rr_loss": 0.21901994943618774,
			"reg_loss_valid": 0.11420426517724991,
			"reg_acc_valid": 0.8633541464805603,
			"rr_loss_valid": 0.22802111506462097,
			"reg_loss_all": 0.0,
			"reg_acc_all": 0.0,
			"rr_loss_all": 0.0,
			"reg_loss_all_valid": 0.0,
			"reg_acc_all_valid": 0.0,
			"rr_loss_all_valid": 0.0,
			"tmle_loss": 0.17699483036994934,
			"l2_loss": 0.0,
			"te_train": 0.04112383350729942,
			"te_corr_train": 0.019549526274204254,
			"te_dr_train": 0.04116220027208328,
			"te_valid": 0.06253483891487122,
			"te_corr_valid": 0.02790933847427368,
			"te_dr_valid": 0.060713864862918854,
			"alpha:t00-tcf0": 0.0,
			"alpha:t00-tcf1": 0.0,
			"alpha:t01-tcf0": 0.0,
			"alpha:t01-tcf1": 0.0,
			"topic0": 0.0,
			"topic0_flip_main": 0.0,
			"topic0_smin_main": 0.0,
			"main_smin_topic0": 0.0,
			"topic0_flip_main_pdelta": 0.0,
			"topic0_flip_main_logpdelta": 0.0,
			"topic0_flip_emb_diff": 0.0,
			"topic0_flip_main_pdelta_m1t1": 0.0,
			"topic0_flip_main_pdelta_m0t1": 0.0,
			"topic0_flip_main_pdelta_m0t0": 0.0,
			"topic0_flip_main_pdelta_m1t0": 0.0,
			"topic0_flip_main_pdelta_smin": 0.0,
			"topic0_flip_main_pdelta_smaj": 0.0,
			"topic0_flip_main_pdelta_all": 0.0,
			"topic0_pos_con_loss": 0.0,
			"topic0_neg_con_loss": 0.0,
			"topic0_last_emb_norm": 0.0,
			"topic0_te_loss": 0.0
		},
		"label_corr_dict": null
	},
	{
		"classifier_acc_dict": {
			"main": 0.0,
			"pp_emb_norm": 0.0,
			"main_xent": 0.0,
			"emb_norm": 15.160093307495117,
			"reg_loss": 0.001388268661685288,
			"reg_acc": 0.9988571405410767,
			"rr_loss": 0.21366514265537262,
			"reg_loss_valid": 0.11485335975885391,
			"reg_acc_valid": 0.8654245734214783,
			"rr_loss_valid": 0.23022285103797913,
			"reg_loss_all": 0.0,
			"reg_acc_all": 0.0,
			"rr_loss_all": 0.0,
			"reg_loss_all_valid": 0.0,
			"reg_acc_all_valid": 0.0,
			"rr_loss_all_valid": 0.0,
			"tmle_loss": 0.17514708638191223,
			"l2_loss": 0.0,
			"te_train": 0.039430174976587296,
			"te_corr_train": 0.019530348479747772,
			"te_dr_train": 0.03951616212725639,
			"te_valid": 0.0646827220916748,
			"te_corr_valid": 0.028705615550279617,
			"te_dr_valid": 0.0601147785782814,
			"alpha:t00-tcf0": 0.0,
			"alpha:t00-tcf1": 0.0,
			"alpha:t01-tcf0": 0.0,
			"alpha:t01-tcf1": 0.0,
			"topic0": 0.0,
			"topic0_flip_main": 0.0,
			"topic0_smin_main": 0.0,
			"main_smin_topic0": 0.0,
			"topic0_flip_main_pdelta": 0.0,
			"topic0_flip_main_logpdelta": 0.0,
			"topic0_flip_emb_diff": 0.0,
			"topic0_flip_main_pdelta_m1t1": 0.0,
			"topic0_flip_main_pdelta_m0t1": 0.0,
			"topic0_flip_main_pdelta_m0t0": 0.0,
			"topic0_flip_main_pdelta_m1t0": 0.0,
			"topic0_flip_main_pdelta_smin": 0.0,
			"topic0_flip_main_pdelta_smaj": 0.0,
			"topic0_flip_main_pdelta_all": 0.0,
			"topic0_pos_con_loss": 0.0,
			"topic0_neg_con_loss": 0.0,
			"topic0_last_emb_norm": 0.0,
			"topic0_te_loss": 0.0
		},
		"label_corr_dict": null
	},
	{
		"classifier_acc_dict": {
			"main": 0.0,
			"pp_emb_norm": 0.0,
			"main_xent": 0.0,
			"emb_norm": 15.104150772094727,
			"reg_loss": 0.001735034165903926,
			"reg_acc": 0.9988571405410767,
			"rr_loss": 0.20288929343223572,
			"reg_loss_valid": 0.11661092936992645,
			"reg_acc_valid": 0.8654245734214783,
			"rr_loss_valid": 0.23282568156719208,
			"reg_loss_all": 0.0,
			"reg_acc_all": 0.0,
			"rr_loss_all": 0.0,
			"reg_loss_all_valid": 0.0,
			"reg_acc_all_valid": 0.0,
			"rr_loss_all_valid": 0.0,
			"tmle_loss": 0.1716715395450592,
			"l2_loss": 0.0,
			"te_train": 0.03335157036781311,
			"te_corr_train": 0.017431005835533142,
			"te_dr_train": 0.033505748957395554,
			"te_valid": 0.06366446614265442,
			"te_corr_valid": 0.027645787224173546,
			"te_dr_valid": 0.05810365080833435,
			"alpha:t00-tcf0": 0.0,
			"alpha:t00-tcf1": 0.0,
			"alpha:t01-tcf0": 0.0,
			"alpha:t01-tcf1": 0.0,
			"topic0": 0.0,
			"topic0_flip_main": 0.0,
			"topic0_smin_main": 0.0,
			"main_smin_topic0": 0.0,
			"topic0_flip_main_pdelta": 0.0,
			"topic0_flip_main_logpdelta": 0.0,
			"topic0_flip_emb_diff": 0.0,
			"topic0_flip_main_pdelta_m1t1": 0.0,
			"topic0_flip_main_pdelta_m0t1": 0.0,
			"topic0_flip_main_pdelta_m0t0": 0.0,
			"topic0_flip_main_pdelta_m1t0": 0.0,
			"topic0_flip_main_pdelta_smin": 0.0,
			"topic0_flip_main_pdelta_smaj": 0.0,
			"topic0_flip_main_pdelta_all": 0.0,
			"topic0_pos_con_loss": 0.0,
			"topic0_neg_con_loss": 0.0,
			"topic0_last_emb_norm": 0.0,
			"topic0_te_loss": 0.0
		},
		"label_corr_dict": null
	},
	{
		"classifier_acc_dict": {
			"main": 0.0,
			"pp_emb_norm": 0.0,
			"main_xent": 0.0,
			"emb_norm": 15.132704734802246,
			"reg_loss": 0.002180203329771757,
			"reg_acc": 0.9988571405410767,
			"rr_loss": 0.21502220630645752,
			"reg_loss_valid": 0.11800704151391983,
			"reg_acc_valid": 0.8633541464805603,
			"rr_loss_valid": 0.23533788323402405,
			"reg_loss_all": 0.0,
			"reg_acc_all": 0.0,
			"rr_loss_all": 0.0,
			"reg_loss_all_valid": 0.0,
			"reg_acc_all_valid": 0.0,
			"rr_loss_all_valid": 0.0,
			"tmle_loss": 0.1792992800474167,
			"l2_loss": 0.0,
			"te_train": 0.03592487424612045,
			"te_corr_train": 0.01718454249203205,
			"te_dr_train": 0.03600095584988594,
			"te_valid": 0.06474720686674118,
			"te_corr_valid": 0.02828449197113514,
			"te_dr_valid": 0.057816263288259506,
			"alpha:t00-tcf0": 0.0,
			"alpha:t00-tcf1": 0.0,
			"alpha:t01-tcf0": 0.0,
			"alpha:t01-tcf1": 0.0,
			"topic0": 0.0,
			"topic0_flip_main": 0.0,
			"topic0_smin_main": 0.0,
			"main_smin_topic0": 0.0,
			"topic0_flip_main_pdelta": 0.0,
			"topic0_flip_main_logpdelta": 0.0,
			"topic0_flip_emb_diff": 0.0,
			"topic0_flip_main_pdelta_m1t1": 0.0,
			"topic0_flip_main_pdelta_m0t1": 0.0,
			"topic0_flip_main_pdelta_m0t0": 0.0,
			"topic0_flip_main_pdelta_m1t0": 0.0,
			"topic0_flip_main_pdelta_smin": 0.0,
			"topic0_flip_main_pdelta_smaj": 0.0,
			"topic0_flip_main_pdelta_all": 0.0,
			"topic0_pos_con_loss": 0.0,
			"topic0_neg_con_loss": 0.0,
			"topic0_last_emb_norm": 0.0,
			"topic0_te_loss": 0.0
		},
		"label_corr_dict": null
	},
	{
		"classifier_acc_dict": {
			"main": 0.0,
			"pp_emb_norm": 0.0,
			"main_xent": 0.0,
			"emb_norm": 15.077062606811523,
			"reg_loss": 0.0036666980013251305,
			"reg_acc": 0.9994285702705383,
			"rr_loss": 0.21787381172180176,
			"reg_loss_valid": 0.11915617436170578,
			"reg_acc_valid": 0.8654245734214783,
			"rr_loss_valid": 0.23421820998191833,
			"reg_loss_all": 0.0,
			"reg_acc_all": 0.0,
			"rr_loss_all": 0.0,
			"reg_loss_all_valid": 0.0,
			"reg_acc_all_valid": 0.0,
			"rr_loss_all_valid": 0.0,
			"tmle_loss": 0.18072156608104706,
			"l2_loss": 0.0,
			"te_train": 0.03758665546774864,
			"te_corr_train": 0.017907408997416496,
			"te_dr_train": 0.037841055542230606,
			"te_valid": 0.05779564380645752,
			"te_corr_valid": 0.026363760232925415,
			"te_dr_valid": 0.058519937098026276,
			"alpha:t00-tcf0": 0.0,
			"alpha:t00-tcf1": 0.0,
			"alpha:t01-tcf0": 0.0,
			"alpha:t01-tcf1": 0.0,
			"topic0": 0.0,
			"topic0_flip_main": 0.0,
			"topic0_smin_main": 0.0,
			"main_smin_topic0": 0.0,
			"topic0_flip_main_pdelta": 0.0,
			"topic0_flip_main_logpdelta": 0.0,
			"topic0_flip_emb_diff": 0.0,
			"topic0_flip_main_pdelta_m1t1": 0.0,
			"topic0_flip_main_pdelta_m0t1": 0.0,
			"topic0_flip_main_pdelta_m0t0": 0.0,
			"topic0_flip_main_pdelta_m1t0": 0.0,
			"topic0_flip_main_pdelta_smin": 0.0,
			"topic0_flip_main_pdelta_smaj": 0.0,
			"topic0_flip_main_pdelta_all": 0.0,
			"topic0_pos_con_loss": 0.0,
			"topic0_neg_con_loss": 0.0,
			"topic0_last_emb_norm": 0.0,
			"topic0_te_loss": 0.0
		},
		"label_corr_dict": null
	},
	{
		"classifier_acc_dict": {
			"main": 0.0,
			"pp_emb_norm": 0.0,
			"main_xent": 0.0,
			"emb_norm": 15.031595230102539,
			"reg_loss": 0.0068527343682944775,
			"reg_acc": 0.9994285702705383,
			"rr_loss": 0.21079455316066742,
			"reg_loss_valid": 0.11677483469247818,
			"reg_acc_valid": 0.8592133522033691,
			"rr_loss_valid": 0.21439629793167114,
			"reg_loss_all": 0.0,
			"reg_acc_all": 0.0,
			"rr_loss_all": 0.0,
			"reg_loss_all_valid": 0.0,
			"reg_acc_all_valid": 0.0,
			"rr_loss_all_valid": 0.0,
			"tmle_loss": 0.18533627688884735,
			"l2_loss": 0.0,
			"te_train": 0.03284067660570145,
			"te_corr_train": 0.01760481297969818,
			"te_dr_train": 0.03333288058638573,
			"te_valid": 0.05818163976073265,
			"te_corr_valid": 0.03219584375619888,
			"te_dr_valid": 0.05571187660098076,
			"alpha:t00-tcf0": 0.0,
			"alpha:t00-tcf1": 0.0,
			"alpha:t01-tcf0": 0.0,
			"alpha:t01-tcf1": 0.0,
			"topic0": 0.0,
			"topic0_flip_main": 0.0,
			"topic0_smin_main": 0.0,
			"main_smin_topic0": 0.0,
			"topic0_flip_main_pdelta": 0.0,
			"topic0_flip_main_logpdelta": 0.0,
			"topic0_flip_emb_diff": 0.0,
			"topic0_flip_main_pdelta_m1t1": 0.0,
			"topic0_flip_main_pdelta_m0t1": 0.0,
			"topic0_flip_main_pdelta_m0t0": 0.0,
			"topic0_flip_main_pdelta_m1t0": 0.0,
			"topic0_flip_main_pdelta_smin": 0.0,
			"topic0_flip_main_pdelta_smaj": 0.0,
			"topic0_flip_main_pdelta_all": 0.0,
			"topic0_pos_con_loss": 0.0,
			"topic0_neg_con_loss": 0.0,
			"topic0_last_emb_norm": 0.0,
			"topic0_te_loss": 0.0
		},
		"label_corr_dict": null
	},
	{
		"classifier_acc_dict": {
			"main": 0.0,
			"pp_emb_norm": 0.0,
			"main_xent": 0.0,
			"emb_norm": 14.805727005004883,
			"reg_loss": 0.013493317179381847,
			"reg_acc": 0.9988571405410767,
			"rr_loss": 0.21620140969753265,
			"reg_loss_valid": 0.10597284883260727,
			"reg_acc_valid": 0.8819877505302429,
			"rr_loss_valid": 0.24551822245121002,
			"reg_loss_all": 0.0,
			"reg_acc_all": 0.0,
			"rr_loss_all": 0.0,
			"reg_loss_all_valid": 0.0,
			"reg_acc_all_valid": 0.0,
			"rr_loss_all_valid": 0.0,
			"tmle_loss": 0.19051623344421387,
			"l2_loss": 0.0,
			"te_train": 0.03634164109826088,
			"te_corr_train": 0.020614175125956535,
			"te_dr_train": 0.0369303897023201,
			"te_valid": 0.07450318336486816,
			"te_corr_valid": 0.03313089907169342,
			"te_dr_valid": 0.08325237035751343,
			"alpha:t00-tcf0": 0.0,
			"alpha:t00-tcf1": 0.0,
			"alpha:t01-tcf0": 0.0,
			"alpha:t01-tcf1": 0.0,
			"topic0": 0.0,
			"topic0_flip_main": 0.0,
			"topic0_smin_main": 0.0,
			"main_smin_topic0": 0.0,
			"topic0_flip_main_pdelta": 0.0,
			"topic0_flip_main_logpdelta": 0.0,
			"topic0_flip_emb_diff": 0.0,
			"topic0_flip_main_pdelta_m1t1": 0.0,
			"topic0_flip_main_pdelta_m0t1": 0.0,
			"topic0_flip_main_pdelta_m0t0": 0.0,
			"topic0_flip_main_pdelta_m1t0": 0.0,
			"topic0_flip_main_pdelta_smin": 0.0,
			"topic0_flip_main_pdelta_smaj": 0.0,
			"topic0_flip_main_pdelta_all": 0.0,
			"topic0_pos_con_loss": 0.0,
			"topic0_neg_con_loss": 0.0,
			"topic0_last_emb_norm": 0.0,
			"topic0_te_loss": 0.0
		},
		"label_corr_dict": null
	}
]