[
	{
		"classifier_acc_dict": {
			"main": 0.5077838897705078,
			"pp_emb_norm": 15.329225540161133,
			"main_xent": 1.9854438304901123,
			"emb_norm": 15.674142837524414,
			"topic0": 0.5,
			"topic0_flip_main": 0.5077838897705078,
			"topic0_smin_main": 0.5077342987060547,
			"main_smin_topic0": 0.5077342987060547,
			"topic0_flip_main_pdelta": 0.001719214371405542,
			"topic0_flip_main_logpdelta": 0.022802619263529778,
			"topic0_flip_emb_diff": 0.7790513038635254,
			"topic0_flip_main_pdelta_m1t1": 0.002257952466607094,
			"topic0_flip_main_pdelta_m0t1": 0.0018510428490117192,
			"topic0_flip_main_pdelta_m0t0": 0.0014942827401682734,
			"topic0_flip_main_pdelta_m1t0": 0.001372354687191546,
			"topic0_flip_main_pdelta_smin": 0.0015836568782106042,
			"topic0_flip_main_pdelta_smaj": 0.0018268486019223928,
			"topic0_flip_main_pdelta_all": 0.001719214371405542,
			"topic0_pos_con_loss": 0.0,
			"topic0_neg_con_loss": 0.0,
			"topic0_last_emb_norm": 0.0,
			"topic0_te_loss": 0.04012536630034447
		},
		"label_corr_dict": null
	},
	{
		"classifier_acc_dict": {
			"main": 0.5077838897705078,
			"pp_emb_norm": 15.231486320495605,
			"main_xent": 1.4614551067352295,
			"emb_norm": 15.469350814819336,
			"topic0": 0.5,
			"topic0_flip_main": 0.5077838897705078,
			"topic0_smin_main": 0.5077342987060547,
			"main_smin_topic0": 0.5077342987060547,
			"topic0_flip_main_pdelta": 0.0038717687129974365,
			"topic0_flip_main_logpdelta": 0.017578864470124245,
			"topic0_flip_emb_diff": 0.3755294680595398,
			"topic0_flip_main_pdelta_m1t1": 0.004790641833096743,
			"topic0_flip_main_pdelta_m0t1": 0.00410094391554594,
			"topic0_flip_main_pdelta_m0t0": 0.003665694734081626,
			"topic0_flip_main_pdelta_m1t0": 0.0030940708238631487,
			"topic0_flip_main_pdelta_smin": 0.003562299534678459,
			"topic0_flip_main_pdelta_smaj": 0.004084849264472723,
			"topic0_flip_main_pdelta_all": 0.0038717687129974365,
			"topic0_pos_con_loss": 0.0,
			"topic0_neg_con_loss": 0.0,
			"topic0_last_emb_norm": 0.0,
			"topic0_te_loss": 0.04001862555742264
		},
		"label_corr_dict": null
	},
	{
		"classifier_acc_dict": {
			"main": 0.5077838897705078,
			"pp_emb_norm": 15.240193367004395,
			"main_xent": 1.0920884609222412,
			"emb_norm": 15.24710750579834,
			"topic0": 0.5,
			"topic0_flip_main": 0.5077838897705078,
			"topic0_smin_main": 0.5077342987060547,
			"main_smin_topic0": 0.5077342987060547,
			"topic0_flip_main_pdelta": 0.00840716902166605,
			"topic0_flip_main_logpdelta": 0.021329296752810478,
			"topic0_flip_emb_diff": 0.27674221992492676,
			"topic0_flip_main_pdelta_m1t1": 0.009450094774365425,
			"topic0_flip_main_pdelta_m0t1": 0.008378063328564167,
			"topic0_flip_main_pdelta_m0t0": 0.008321606554090977,
			"topic0_flip_main_pdelta_m1t0": 0.007513273507356644,
			"topic0_flip_main_pdelta_smin": 0.007980824448168278,
			"topic0_flip_main_pdelta_smaj": 0.008668405003845692,
			"topic0_flip_main_pdelta_all": 0.00840716902166605,
			"topic0_pos_con_loss": 0.0,
			"topic0_neg_con_loss": 0.0,
			"topic0_last_emb_norm": 0.0,
			"topic0_te_loss": 0.03999149054288864
		},
		"label_corr_dict": null
	},
	{
		"classifier_acc_dict": {
			"main": 0.5077838897705078,
			"pp_emb_norm": 16.49852180480957,
			"main_xent": 0.8906648755073547,
			"emb_norm": 16.03624725341797,
			"topic0": 0.5,
			"topic0_flip_main": 0.5077838897705078,
			"topic0_smin_main": 0.5077342987060547,
			"main_smin_topic0": 0.5077342987060547,
			"topic0_flip_main_pdelta": 0.016878217458724976,
			"topic0_flip_main_logpdelta": 0.03449828922748566,
			"topic0_flip_emb_diff": 0.28754132986068726,
			"topic0_flip_main_pdelta_m1t1": 0.019383156672120094,
			"topic0_flip_main_pdelta_m0t1": 0.017328836023807526,
			"topic0_flip_main_pdelta_m0t0": 0.016065137460827827,
			"topic0_flip_main_pdelta_m1t0": 0.014987342990934849,
			"topic0_flip_main_pdelta_smin": 0.016117483377456665,
			"topic0_flip_main_pdelta_smaj": 0.0172212403267622,
			"topic0_flip_main_pdelta_all": 0.016878217458724976,
			"topic0_pos_con_loss": 0.0,
			"topic0_neg_con_loss": 0.0,
			"topic0_last_emb_norm": 0.0,
			"topic0_te_loss": 0.03990355506539345
		},
		"label_corr_dict": null
	},
	{
		"classifier_acc_dict": {
			"main": 0.45604395866394043,
			"pp_emb_norm": 16.180326461791992,
			"main_xent": 0.7015554308891296,
			"emb_norm": 16.312267303466797,
			"topic0": 0.5,
			"topic0_flip_main": 0.4752747118473053,
			"topic0_smin_main": 0.6141947507858276,
			"main_smin_topic0": 0.5077342987060547,
			"topic0_flip_main_pdelta": 0.022503351792693138,
			"topic0_flip_main_logpdelta": 0.045072197914123535,
			"topic0_flip_emb_diff": 0.2789979875087738,
			"topic0_flip_main_pdelta_m1t1": 0.029475495219230652,
			"topic0_flip_main_pdelta_m0t1": 0.02533378265798092,
			"topic0_flip_main_pdelta_m0t0": 0.01745237410068512,
			"topic0_flip_main_pdelta_m1t0": 0.017883162945508957,
			"topic0_flip_main_pdelta_smin": 0.021382112056016922,
			"topic0_flip_main_pdelta_smaj": 0.022937750443816185,
			"topic0_flip_main_pdelta_all": 0.022503351792693138,
			"topic0_pos_con_loss": 0.0,
			"topic0_neg_con_loss": 0.0,
			"topic0_last_emb_norm": 0.0,
			"topic0_te_loss": 0.03963659703731537
		},
		"label_corr_dict": null
	},
	{
		"classifier_acc_dict": {
			"main": 0.47893771529197693,
			"pp_emb_norm": 16.28188705444336,
			"main_xent": 0.6965304613113403,
			"emb_norm": 16.476978302001953,
			"topic0": 0.5,
			"topic0_flip_main": 0.5073260068893433,
			"topic0_smin_main": 0.6378526091575623,
			"main_smin_topic0": 0.5077342987060547,
			"topic0_flip_main_pdelta": 0.03625109791755676,
			"topic0_flip_main_logpdelta": 0.07265684753656387,
			"topic0_flip_emb_diff": 0.30035001039505005,
			"topic0_flip_main_pdelta_m1t1": 0.04730235040187836,
			"topic0_flip_main_pdelta_m0t1": 0.04377856105566025,
			"topic0_flip_main_pdelta_m0t0": 0.026331553235650063,
			"topic0_flip_main_pdelta_m1t0": 0.028189297765493393,
			"topic0_flip_main_pdelta_smin": 0.035425346344709396,
			"topic0_flip_main_pdelta_smaj": 0.03669441491365433,
			"topic0_flip_main_pdelta_all": 0.03625109791755676,
			"topic0_pos_con_loss": 0.0,
			"topic0_neg_con_loss": 0.0,
			"topic0_last_emb_norm": 0.0,
			"topic0_te_loss": 0.03934584930539131
		},
		"label_corr_dict": null
	},
	{
		"classifier_acc_dict": {
			"main": 0.4913003742694855,
			"pp_emb_norm": 16.65213966369629,
			"main_xent": 0.6978150606155396,
			"emb_norm": 16.672794342041016,
			"topic0": 0.5,
			"topic0_flip_main": 0.5073260068893433,
			"topic0_smin_main": 0.603275716304779,
			"main_smin_topic0": 0.5077342987060547,
			"topic0_flip_main_pdelta": 0.021512316539883614,
			"topic0_flip_main_logpdelta": 0.04316991567611694,
			"topic0_flip_emb_diff": 0.24008682370185852,
			"topic0_flip_main_pdelta_m1t1": 0.022609304636716843,
			"topic0_flip_main_pdelta_m0t1": 0.021537218242883682,
			"topic0_flip_main_pdelta_m0t0": 0.021312806755304337,
			"topic0_flip_main_pdelta_m1t0": 0.021206693723797798,
			"topic0_flip_main_pdelta_smin": 0.02129989117383957,
			"topic0_flip_main_pdelta_smaj": 0.021284062415361404,
			"topic0_flip_main_pdelta_all": 0.021512316539883614,
			"topic0_pos_con_loss": 0.0,
			"topic0_neg_con_loss": 0.0,
			"topic0_last_emb_norm": 0.0,
			"topic0_te_loss": 0.0391194112598896
		},
		"label_corr_dict": null
	},
	{
		"classifier_acc_dict": {
			"main": 0.4592490792274475,
			"pp_emb_norm": 16.87369728088379,
			"main_xent": 0.7016861438751221,
			"emb_norm": 16.920576095581055,
			"topic0": 0.5,
			"topic0_flip_main": 0.49267399311065674,
			"topic0_smin_main": 0.5787079334259033,
			"main_smin_topic0": 0.5077342987060547,
			"topic0_flip_main_pdelta": 0.026455573737621307,
			"topic0_flip_main_logpdelta": 0.052996426820755005,
			"topic0_flip_emb_diff": 0.23596350848674774,
			"topic0_flip_main_pdelta_m1t1": 0.020971164107322693,
			"topic0_flip_main_pdelta_m0t1": 0.023235345259308815,
			"topic0_flip_main_pdelta_m0t0": 0.03140641003847122,
			"topic0_flip_main_pdelta_m1t0": 0.02912960760295391,
			"topic0_flip_main_pdelta_smin": 0.026354065164923668,
			"topic0_flip_main_pdelta_smaj": 0.02602529339492321,
			"topic0_flip_main_pdelta_all": 0.026455573737621307,
			"topic0_pos_con_loss": 0.0,
			"topic0_neg_con_loss": 0.0,
			"topic0_last_emb_norm": 0.0,
			"topic0_te_loss": 0.03899189084768295
		},
		"label_corr_dict": null
	},
	{
		"classifier_acc_dict": {
			"main": 0.4674908518791199,
			"pp_emb_norm": 17.222469329833984,
			"main_xent": 0.7050793170928955,
			"emb_norm": 17.1322021484375,
			"topic0": 0.5,
			"topic0_flip_main": 0.5082417726516724,
			"topic0_smin_main": 0.5978161692619324,
			"main_smin_topic0": 0.5077342987060547,
			"topic0_flip_main_pdelta": 0.012294120155274868,
			"topic0_flip_main_logpdelta": 0.02460019290447235,
			"topic0_flip_emb_diff": 0.12901683151721954,
			"topic0_flip_main_pdelta_m1t1": 0.014962208457291126,
			"topic0_flip_main_pdelta_m0t1": 0.01400829665362835,
			"topic0_flip_main_pdelta_m0t0": 0.009940453805029392,
			"topic0_flip_main_pdelta_m1t0": 0.010597641579806805,
			"topic0_flip_main_pdelta_smin": 0.012206961400806904,
			"topic0_flip_main_pdelta_smaj": 0.0121105732396245,
			"topic0_flip_main_pdelta_all": 0.012294120155274868,
			"topic0_pos_con_loss": 0.0,
			"topic0_neg_con_loss": 0.0,
			"topic0_last_emb_norm": 0.0,
			"topic0_te_loss": 0.03888535127043724
		},
		"label_corr_dict": null
	},
	{
		"classifier_acc_dict": {
			"main": 0.5077838897705078,
			"pp_emb_norm": 17.286550521850586,
			"main_xent": 0.7127216458320618,
			"emb_norm": 17.215232849121094,
			"topic0": 0.5,
			"topic0_flip_main": 0.5077838897705078,
			"topic0_smin_main": 0.5077342987060547,
			"main_smin_topic0": 0.5077342987060547,
			"topic0_flip_main_pdelta": 0.015456430613994598,
			"topic0_flip_main_logpdelta": 0.03369934856891632,
			"topic0_flip_emb_diff": 0.1545761674642563,
			"topic0_flip_main_pdelta_m1t1": 0.01994413137435913,
			"topic0_flip_main_pdelta_m0t1": 0.01845763809978962,
			"topic0_flip_main_pdelta_m0t0": 0.011355407536029816,
			"topic0_flip_main_pdelta_m1t0": 0.012201795354485512,
			"topic0_flip_main_pdelta_smin": 0.015032248571515083,
			"topic0_flip_main_pdelta_smaj": 0.015639912337064743,
			"topic0_flip_main_pdelta_all": 0.015456430613994598,
			"topic0_pos_con_loss": 0.0,
			"topic0_neg_con_loss": 0.0,
			"topic0_last_emb_norm": 0.0,
			"topic0_te_loss": 0.03878935053944588
		},
		"label_corr_dict": null
	},
	{
		"classifier_acc_dict": {
			"main": 0.4958791136741638,
			"pp_emb_norm": 17.441957473754883,
			"main_xent": 0.7142383456230164,
			"emb_norm": 17.32689666748047,
			"topic0": 0.5,
			"topic0_flip_main": 0.5077838897705078,
			"topic0_smin_main": 0.5677888989448547,
			"main_smin_topic0": 0.5077342987060547,
			"topic0_flip_main_pdelta": 0.019807269796729088,
			"topic0_flip_main_logpdelta": 0.03978750482201576,
			"topic0_flip_emb_diff": 0.1558757871389389,
			"topic0_flip_main_pdelta_m1t1": 0.025790415704250336,
			"topic0_flip_main_pdelta_m0t1": 0.023395778611302376,
			"topic0_flip_main_pdelta_m0t0": 0.014755320735275745,
			"topic0_flip_main_pdelta_m1t0": 0.01561933197081089,
			"topic0_flip_main_pdelta_smin": 0.019196785986423492,
			"topic0_flip_main_pdelta_smaj": 0.019832072779536247,
			"topic0_flip_main_pdelta_all": 0.019807269796729088,
			"topic0_pos_con_loss": 0.0,
			"topic0_neg_con_loss": 0.0,
			"topic0_last_emb_norm": 0.0,
			"topic0_te_loss": 0.038752272725105286
		},
		"label_corr_dict": null
	},
	{
		"classifier_acc_dict": {
			"main": 0.5077838897705078,
			"pp_emb_norm": 17.354509353637695,
			"main_xent": 0.7424363493919373,
			"emb_norm": 17.32744789123535,
			"topic0": 0.5,
			"topic0_flip_main": 0.5077838897705078,
			"topic0_smin_main": 0.5077342987060547,
			"main_smin_topic0": 0.5077342987060547,
			"topic0_flip_main_pdelta": 0.012441485188901424,
			"topic0_flip_main_logpdelta": 0.02547198161482811,
			"topic0_flip_emb_diff": 0.11582878232002258,
			"topic0_flip_main_pdelta_m1t1": 0.015145023353397846,
			"topic0_flip_main_pdelta_m0t1": 0.013969327323138714,
			"topic0_flip_main_pdelta_m0t0": 0.010102704167366028,
			"topic0_flip_main_pdelta_m1t0": 0.01075899787247181,
			"topic0_flip_main_pdelta_smin": 0.012260605581104755,
			"topic0_flip_main_pdelta_smaj": 0.012342382222414017,
			"topic0_flip_main_pdelta_all": 0.012441485188901424,
			"topic0_pos_con_loss": 0.0,
			"topic0_neg_con_loss": 0.0,
			"topic0_last_emb_norm": 0.0,
			"topic0_te_loss": 0.03873999044299126
		},
		"label_corr_dict": null
	},
	{
		"classifier_acc_dict": {
			"main": 0.4734432101249695,
			"pp_emb_norm": 17.554203033447266,
			"main_xent": 0.7115268111228943,
			"emb_norm": 17.43540382385254,
			"topic0": 0.5,
			"topic0_flip_main": 0.5018315315246582,
			"topic0_smin_main": 0.6123749017715454,
			"main_smin_topic0": 0.5077342987060547,
			"topic0_flip_main_pdelta": 0.010808870196342468,
			"topic0_flip_main_logpdelta": 0.02163057029247284,
			"topic0_flip_emb_diff": 0.10016327351331711,
			"topic0_flip_main_pdelta_m1t1": 0.010503673925995827,
			"topic0_flip_main_pdelta_m0t1": 0.010716456919908524,
			"topic0_flip_main_pdelta_m0t0": 0.011361545883119106,
			"topic0_flip_main_pdelta_m1t0": 0.010815813206136227,
			"topic0_flip_main_pdelta_smin": 0.01076916791498661,
			"topic0_flip_main_pdelta_smaj": 0.01079398114234209,
			"topic0_flip_main_pdelta_all": 0.010808870196342468,
			"topic0_pos_con_loss": 0.0,
			"topic0_neg_con_loss": 0.0,
			"topic0_last_emb_norm": 0.0,
			"topic0_te_loss": 0.03867657110095024
		},
		"label_corr_dict": null
	},
	{
		"classifier_acc_dict": {
			"main": 0.46657508611679077,
			"pp_emb_norm": 17.493446350097656,
			"main_xent": 0.7114788889884949,
			"emb_norm": 17.513582229614258,
			"topic0": 0.5,
			"topic0_flip_main": 0.4967948794364929,
			"topic0_smin_main": 0.6178343892097473,
			"main_smin_topic0": 0.5077342987060547,
			"topic0_flip_main_pdelta": 0.015213524922728539,
			"topic0_flip_main_logpdelta": 0.030454717576503754,
			"topic0_flip_emb_diff": 0.1159418448805809,
			"topic0_flip_main_pdelta_m1t1": 0.014581515453755856,
			"topic0_flip_main_pdelta_m0t1": 0.01460838783532381,
			"topic0_flip_main_pdelta_m0t0": 0.016371361911296844,
			"topic0_flip_main_pdelta_m1t0": 0.015220762230455875,
			"topic0_flip_main_pdelta_smin": 0.014888524077832699,
			"topic0_flip_main_pdelta_smaj": 0.015247263014316559,
			"topic0_flip_main_pdelta_all": 0.015213524922728539,
			"topic0_pos_con_loss": 0.0,
			"topic0_neg_con_loss": 0.0,
			"topic0_last_emb_norm": 0.0,
			"topic0_te_loss": 0.03861679136753082
		},
		"label_corr_dict": null
	},
	{
		"classifier_acc_dict": {
			"main": 0.48351648449897766,
			"pp_emb_norm": 17.51669692993164,
			"main_xent": 0.7060012817382812,
			"emb_norm": 17.547847747802734,
			"topic0": 0.5,
			"topic0_flip_main": 0.5082417726516724,
			"topic0_smin_main": 0.5996360182762146,
			"main_smin_topic0": 0.5077342987060547,
			"topic0_flip_main_pdelta": 0.015977829694747925,
			"topic0_flip_main_logpdelta": 0.03202197328209877,
			"topic0_flip_emb_diff": 0.11480122059583664,
			"topic0_flip_main_pdelta_m1t1": 0.015314864926040173,
			"topic0_flip_main_pdelta_m0t1": 0.015251947566866875,
			"topic0_flip_main_pdelta_m0t0": 0.01715359091758728,
			"topic0_flip_main_pdelta_m1t0": 0.01599939726293087,
			"topic0_flip_main_pdelta_smin": 0.015625562518835068,
			"topic0_flip_main_pdelta_smaj": 0.015994545072317123,
			"topic0_flip_main_pdelta_all": 0.015977829694747925,
			"topic0_pos_con_loss": 0.0,
			"topic0_neg_con_loss": 0.0,
			"topic0_last_emb_norm": 0.0,
			"topic0_te_loss": 0.03855222836136818
		},
		"label_corr_dict": null
	},
	{
		"classifier_acc_dict": {
			"main": 0.4702380895614624,
			"pp_emb_norm": 17.640682220458984,
			"main_xent": 0.7012816667556763,
			"emb_norm": 17.60951042175293,
			"topic0": 0.5,
			"topic0_flip_main": 0.45695969462394714,
			"topic0_smin_main": 0.5923566818237305,
			"main_smin_topic0": 0.5077342987060547,
			"topic0_flip_main_pdelta": 0.01595740206539631,
			"topic0_flip_main_logpdelta": 0.03194871172308922,
			"topic0_flip_emb_diff": 0.10935863852500916,
			"topic0_flip_main_pdelta_m1t1": 0.019288746640086174,
			"topic0_flip_main_pdelta_m0t1": 0.018085304647684097,
			"topic0_flip_main_pdelta_m0t0": 0.012628709897398949,
			"topic0_flip_main_pdelta_m1t0": 0.013866105116903782,
			"topic0_flip_main_pdelta_smin": 0.015726763755083084,
			"topic0_flip_main_pdelta_smaj": 0.015888210386037827,
			"topic0_flip_main_pdelta_all": 0.01595740206539631,
			"topic0_pos_con_loss": 0.0,
			"topic0_neg_con_loss": 0.0,
			"topic0_last_emb_norm": 0.0,
			"topic0_te_loss": 0.03857439383864403
		},
		"label_corr_dict": null
	},
	{
		"classifier_acc_dict": {
			"main": 0.5064102411270142,
			"pp_emb_norm": 17.567764282226562,
			"main_xent": 0.7094693183898926,
			"emb_norm": 17.651647567749023,
			"topic0": 0.5,
			"topic0_flip_main": 0.5077838897705078,
			"topic0_smin_main": 0.5068243741989136,
			"main_smin_topic0": 0.5077342987060547,
			"topic0_flip_main_pdelta": 0.021581029519438744,
			"topic0_flip_main_logpdelta": 0.044242046773433685,
			"topic0_flip_emb_diff": 0.13629139959812164,
			"topic0_flip_main_pdelta_m1t1": 0.027289239689707756,
			"topic0_flip_main_pdelta_m0t1": 0.02564769610762596,
			"topic0_flip_main_pdelta_m0t0": 0.015595351345837116,
			"topic0_flip_main_pdelta_m1t0": 0.01747805066406727,
			"topic0_flip_main_pdelta_smin": 0.021368592977523804,
			"topic0_flip_main_pdelta_smaj": 0.02130059525370598,
			"topic0_flip_main_pdelta_all": 0.021581029519438744,
			"topic0_pos_con_loss": 0.0,
			"topic0_neg_con_loss": 0.0,
			"topic0_last_emb_norm": 0.0,
			"topic0_te_loss": 0.03857685253024101
		},
		"label_corr_dict": null
	},
	{
		"classifier_acc_dict": {
			"main": 0.5082417726516724,
			"pp_emb_norm": 17.13410758972168,
			"main_xent": 0.7747073173522949,
			"emb_norm": 17.434669494628906,
			"topic0": 0.5,
			"topic0_flip_main": 0.5077838897705078,
			"topic0_smin_main": 0.516833484172821,
			"main_smin_topic0": 0.5077342987060547,
			"topic0_flip_main_pdelta": 0.02085142582654953,
			"topic0_flip_main_logpdelta": 0.04241412132978439,
			"topic0_flip_emb_diff": 0.1332973837852478,
			"topic0_flip_main_pdelta_m1t1": 0.025479450821876526,
			"topic0_flip_main_pdelta_m0t1": 0.023859091103076935,
			"topic0_flip_main_pdelta_m0t0": 0.01624804362654686,
			"topic0_flip_main_pdelta_m1t0": 0.01775049790740013,
			"topic0_flip_main_pdelta_smin": 0.020562274381518364,
			"topic0_flip_main_pdelta_smaj": 0.02069460228085518,
			"topic0_flip_main_pdelta_all": 0.02085142582654953,
			"topic0_pos_con_loss": 0.0,
			"topic0_neg_con_loss": 0.0,
			"topic0_last_emb_norm": 0.0,
			"topic0_te_loss": 0.038640230894088745
		},
		"label_corr_dict": null
	},
	{
		"classifier_acc_dict": {
			"main": 0.5032051205635071,
			"pp_emb_norm": 17.195497512817383,
			"main_xent": 0.7448877692222595,
			"emb_norm": 17.290733337402344,
			"topic0": 0.5,
			"topic0_flip_main": 0.5077838897705078,
			"topic0_smin_main": 0.5641492009162903,
			"main_smin_topic0": 0.5077342987060547,
			"topic0_flip_main_pdelta": 0.015764359384775162,
			"topic0_flip_main_logpdelta": 0.03165788948535919,
			"topic0_flip_emb_diff": 0.10887208580970764,
			"topic0_flip_main_pdelta_m1t1": 0.015555423684418201,
			"topic0_flip_main_pdelta_m0t1": 0.016156218945980072,
			"topic0_flip_main_pdelta_m0t0": 0.015766197815537453,
			"topic0_flip_main_pdelta_m1t0": 0.0155933303758502,
			"topic0_flip_main_pdelta_smin": 0.015729881823062897,
			"topic0_flip_main_pdelta_smaj": 0.015506835654377937,
			"topic0_flip_main_pdelta_all": 0.015764359384775162,
			"topic0_pos_con_loss": 0.0,
			"topic0_neg_con_loss": 0.0,
			"topic0_last_emb_norm": 0.0,
			"topic0_te_loss": 0.038612425327301025
		},
		"label_corr_dict": null
	},
	{
		"classifier_acc_dict": {
			"main": 0.47756409645080566,
			"pp_emb_norm": 17.391611099243164,
			"main_xent": 0.6986812949180603,
			"emb_norm": 17.333642959594727,
			"topic0": 0.5,
			"topic0_flip_main": 0.47664836049079895,
			"topic0_smin_main": 0.6132848262786865,
			"main_smin_topic0": 0.5077342987060547,
			"topic0_flip_main_pdelta": 0.017437268048524857,
			"topic0_flip_main_logpdelta": 0.03492630273103714,
			"topic0_flip_emb_diff": 0.11521892249584198,
			"topic0_flip_main_pdelta_m1t1": 0.015712453052401543,
			"topic0_flip_main_pdelta_m0t1": 0.017233707010746002,
			"topic0_flip_main_pdelta_m0t0": 0.018768856301903725,
			"topic0_flip_main_pdelta_m1t0": 0.018159832805395126,
			"topic0_flip_main_pdelta_smin": 0.0175954457372427,
			"topic0_flip_main_pdelta_smaj": 0.016926869750022888,
			"topic0_flip_main_pdelta_all": 0.017437268048524857,
			"topic0_pos_con_loss": 0.0,
			"topic0_neg_con_loss": 0.0,
			"topic0_last_emb_norm": 0.0,
			"topic0_te_loss": 0.03859884664416313
		},
		"label_corr_dict": null
	}
]