[
	{
		"conv_angle_dict": {
			"topic0": {
				"topic0": 0.0,
				"topic1": 0.4404309364679507,
				"main": 0.2887017750416932
			},
			"topic1": {
				"topic0": 0.4404309364679507,
				"topic1": 0.0,
				"main": 0.46466805246521786
			},
			"main": {
				"topic0": 0.2887017750416932,
				"topic1": 0.46466805246521786,
				"main": 0.00010990189218125593
			}
		},
		"classifier_acc_dict": {
			"main": 1.0,
			"topic0": 1.0,
			"topic0_flip_main": 0.0,
			"topic0_flip_main_pdelta": 0.16529102623462677,
			"topic1": 0.976190447807312,
			"topic1_flip_main": 1.0,
			"topic1_flip_main_pdelta": 0.040575359016656876
		}
	},
	{
		"conv_angle_dict": {
			"topic0": {
				"topic0": 0.0,
				"topic1": 0.4377114587044147,
				"main": 0.26728211207705627
			},
			"topic1": {
				"topic0": 0.4377114587044147,
				"topic1": 0.00010990189218125593,
				"main": 0.4544502791943557
			},
			"main": {
				"topic0": 0.26728211207705627,
				"topic1": 0.4544502791943557,
				"main": 0.00015542474911317905
			}
		},
		"classifier_acc_dict": {
			"main": 1.0,
			"topic0": 1.0,
			"topic0_flip_main": 0.0,
			"topic0_flip_main_pdelta": 0.21907000243663788,
			"topic1": 1.0,
			"topic1_flip_main": 1.0,
			"topic1_flip_main_pdelta": 0.05266525223851204
		}
	},
	{
		"conv_angle_dict": {
			"topic0": {
				"topic0": 0.0,
				"topic1": 0.4368497923951222,
				"main": 0.252746919313586
			},
			"topic1": {
				"topic0": 0.4368497923951222,
				"topic1": NaN,
				"main": 0.4487043066640917
			},
			"main": {
				"topic0": 0.252746919313586,
				"topic1": 0.4487043066640917,
				"main": 0.00010990189218125593
			}
		},
		"classifier_acc_dict": {
			"main": 1.0,
			"topic0": 1.0,
			"topic0_flip_main": 0.0,
			"topic0_flip_main_pdelta": 0.26951849460601807,
			"topic1": 1.0,
			"topic1_flip_main": 1.0,
			"topic1_flip_main_pdelta": 0.06332224607467651
		}
	},
	{
		"conv_angle_dict": {
			"topic0": {
				"topic0": 0.0,
				"topic1": 0.4368940747882411,
				"main": 0.24265700338943694
			},
			"topic1": {
				"topic0": 0.4368940747882411,
				"topic1": NaN,
				"main": 0.4454270680638334
			},
			"main": {
				"topic0": 0.24265700338943694,
				"topic1": 0.4454270680638334,
				"main": 0.0
			}
		},
		"classifier_acc_dict": {
			"main": 1.0,
			"topic0": 1.0,
			"topic0_flip_main": 0.0,
			"topic0_flip_main_pdelta": 0.31772279739379883,
			"topic1": 1.0,
			"topic1_flip_main": 1.0,
			"topic1_flip_main_pdelta": 0.07272075861692429
		}
	},
	{
		"conv_angle_dict": {
			"topic0": {
				"topic0": 0.0,
				"topic1": 0.43725561946830716,
				"main": 0.2354002689057569
			},
			"topic1": {
				"topic0": 0.43725561946830716,
				"topic1": 0.00010990189218125593,
				"main": 0.44359350378114354
			},
			"main": {
				"topic0": 0.2354002689057569,
				"topic1": 0.44359350378114354,
				"main": NaN
			}
		},
		"classifier_acc_dict": {
			"main": 1.0,
			"topic0": 1.0,
			"topic0_flip_main": 0.0,
			"topic0_flip_main_pdelta": 0.36358559131622314,
			"topic1": 1.0,
			"topic1_flip_main": 1.0,
			"topic1_flip_main_pdelta": 0.08085537701845169
		}
	},
	{
		"conv_angle_dict": {
			"topic0": {
				"topic0": 0.0,
				"topic1": 0.43768766687880584,
				"main": 0.22998567438672468
			},
			"topic1": {
				"topic0": 0.43768766687880584,
				"topic1": 0.0,
				"main": 0.4426684305490561
			},
			"main": {
				"topic0": 0.22998567438672468,
				"topic1": 0.4426684305490561,
				"main": 0.0
			}
		},
		"classifier_acc_dict": {
			"main": 1.0,
			"topic0": 1.0,
			"topic0_flip_main": 0.0,
			"topic0_flip_main_pdelta": 0.40681901574134827,
			"topic1": 1.0,
			"topic1_flip_main": 1.0,
			"topic1_flip_main_pdelta": 0.08765679597854614
		}
	},
	{
		"conv_angle_dict": {
			"topic0": {
				"topic0": 0.0,
				"topic1": 0.4381411155487039,
				"main": 0.22584276622741037
			},
			"topic1": {
				"topic0": 0.4381411155487039,
				"topic1": NaN,
				"main": 0.442305026539716
			},
			"main": {
				"topic0": 0.22584276622741037,
				"topic1": 0.442305026539716,
				"main": NaN
			}
		},
		"classifier_acc_dict": {
			"main": 1.0,
			"topic0": 1.0,
			"topic0_flip_main": 0.0,
			"topic0_flip_main_pdelta": 0.44721221923828125,
			"topic1": 1.0,
			"topic1_flip_main": 1.0,
			"topic1_flip_main_pdelta": 0.09311705827713013
		}
	},
	{
		"conv_angle_dict": {
			"topic0": {
				"topic0": 0.0,
				"topic1": 0.43861945646357714,
				"main": 0.22262688549319604
			},
			"topic1": {
				"topic0": 0.43861945646357714,
				"topic1": 0.0,
				"main": 0.44226901626459186
			},
			"main": {
				"topic0": 0.22262688549319604,
				"topic1": 0.44226901626459186,
				"main": NaN
			}
		},
		"classifier_acc_dict": {
			"main": 1.0,
			"topic0": 1.0,
			"topic0_flip_main": 0.0,
			"topic0_flip_main_pdelta": 0.4847131669521332,
			"topic1": 1.0,
			"topic1_flip_main": 1.0,
			"topic1_flip_main_pdelta": 0.0973309874534607
		}
	},
	{
		"conv_angle_dict": {
			"topic0": {
				"topic0": 0.0,
				"topic1": 0.43911354475903674,
				"main": 0.22009984830952517
			},
			"topic1": {
				"topic0": 0.43911354475903674,
				"topic1": 0.00010990189218125593,
				"main": 0.4424228852483941
			},
			"main": {
				"topic0": 0.22009984830952517,
				"topic1": 0.4424228852483941,
				"main": 0.00015542474911317905
			}
		},
		"classifier_acc_dict": {
			"main": 1.0,
			"topic0": 1.0,
			"topic0_flip_main": 0.0,
			"topic0_flip_main_pdelta": 0.5193765759468079,
			"topic1": 1.0,
			"topic1_flip_main": 1.0,
			"topic1_flip_main_pdelta": 0.10043957829475403
		}
	},
	{
		"conv_angle_dict": {
			"topic0": {
				"topic0": 0.0,
				"topic1": 0.43960258630360965,
				"main": 0.21808708642486088
			},
			"topic1": {
				"topic0": 0.43960258630360965,
				"topic1": NaN,
				"main": 0.44269282950259115
			},
			"main": {
				"topic0": 0.21808708642486088,
				"topic1": 0.44269282950259115,
				"main": NaN
			}
		},
		"classifier_acc_dict": {
			"main": 1.0,
			"topic0": 1.0,
			"topic0_flip_main": 0.0,
			"topic0_flip_main_pdelta": 0.5512961149215698,
			"topic1": 1.0,
			"topic1_flip_main": 1.0,
			"topic1_flip_main_pdelta": 0.10257145762443542
		}
	},
	{
		"conv_angle_dict": {
			"topic0": {
				"topic0": 0.0,
				"topic1": 0.4400706439892325,
				"main": 0.21646487855148747
			},
			"topic1": {
				"topic0": 0.4400706439892325,
				"topic1": NaN,
				"main": 0.4430339974516333
			},
			"main": {
				"topic0": 0.21646487855148747,
				"topic1": 0.4430339974516333,
				"main": 0.0001903556712910695
			}
		},
		"classifier_acc_dict": {
			"main": 1.0,
			"topic0": 1.0,
			"topic0_flip_main": 0.0,
			"topic0_flip_main_pdelta": 0.5805882811546326,
			"topic1": 1.0,
			"topic1_flip_main": 1.0,
			"topic1_flip_main_pdelta": 0.10383918136358261
		}
	}
]